augmentRNA/__init__.py
augmentRNA/augmentation.py
augmentRNA-1.0.1.dist-info/METADATA
augmentRNA-1.0.1.dist-info/WHEEL
augmentRNA-1.0.1.dist-info/augmentation.py
augmentRNA-1.0.1.dist-info/top_level.txt
augmentRNA-1.0.1.dist-info/RECORD
