Metadata-Version: 2.1
Name: augmentRNA
Version: 1.0.1
Summary: Lightweight package that allows for the generation of augmented RNA-seq data from a base dataset, for expanding training datasets or large-scale dataset analysis.
Author: Christian de Frondeville
Requires-Dist: scipy
Requires-Dist: numpy
Requires-Dist: tqdm
